telectric/__init__.py
telectric/core.py
telectric-1.2.dist-info/LICENSE
telectric-1.2.dist-info/METADATA
telectric-1.2.dist-info/WHEEL
telectric-1.2.dist-info/top_level.txt
telectric-1.2.dist-info/RECORD
